{"name": "2297", "key": "2297", "state": "NSW", "pops": 1801, "crime": {"total": 133, "Assault and related offences": 13, "Robbery": 1, "Stalking, harassment and threatening behaviour": 6, "Other crimes against the person": 1, "Property damage": 17, "Burglary/Break and enter": 17, "Theft": 29, "Deception": 8, "Cultivate or manufacture drugs": 1, "Drug use and possession": 4, "Other drug offences": 1, "Disorderly and offensive conduct": 1, "Public nuisance offences": 1, "Justice procedures offences": 11, "Transport regulation offences": 2, "Other government regulatory offences": 1, "Miscellaneous offences": 19}, "crime_categories": {"property_crimes": {"number": 63, "rank": 79.12}, "violent_crimes": {"number": 14, "rank": 63.9}}, "bounds": [151.74038418400005, -32.911829360999945, 151.76008166200006, -32.90334017099995], "sqkm": 0.801, "cr": 48.37, "borders": [{"name": "2292", "key": "2292", "cr": 67.81}, {"name": "2293", "key": "2293", "cr": 60.67}, {"name": "2294", "key": "2294", "cr": 52.05}, {"name": "2296", "key": "2296", "cr": 59.34}, {"name": "2304", "key": "2304", "cr": 91.84}]}