{"name": "3221", "key": "3221", "state": "VIC", "pops": 810, "crime": {"total": 12, "Theft": 7, "Burglary/Break and enter": 1, "Justice procedures offences": 1, "Breaches of orders": 1, "Property damage": 2}, "crime_categories": {"property_crimes": {"number": 10, "rank": 30.41}, "violent_crimes": {"number": 0, "rank": 0.0}}, "bounds": [144.08518602200002, -38.20016078699996, 144.293681727, -38.10050678199996], "sqkm": 111.22540000000001, "cr": 16.48, "borders": [{"name": "3213", "key": "3213", "cr": 53.53}, {"name": "3216", "key": "3216", "cr": 93.24}, {"name": "3217", "key": "3217", "cr": 68.64}, {"name": "3218", "key": "3218", "cr": 74.98}, {"name": "3240", "key": "3240", "cr": 39.86}, {"name": "3241", "key": "3241", "cr": 49.51}, {"name": "3321", "key": "3321", "cr": 19.86}, {"name": "3331", "key": "3331", "cr": 50.23}]}