{"name": "3232", "key": "3232", "state": "VIC", "pops": 1327, "crime": {"total": 112, "Assault and related offences": 6, "Robbery": 1, "Stalking, harassment and threatening behaviour": 4, "Other crimes against the person": 7, "Arson": 1, "Property damage": 21, "Burglary/Break and enter": 12, "Theft": 34, "Deception": 6, "Drug use and possession": 2, "Disorderly and offensive conduct": 1, "Public nuisance offences": 1, "Justice procedures offences": 1, "Breaches of orders": 9, "Miscellaneous offences": 6}, "bounds": [143.8245384380001, -38.57940434499994, 144.0086109020001, -38.46713278699994], "cr": 46.09, "borders": [{"name": "3231", "key": "3231", "cr": 32.99}, {"name": "3234", "key": "3234", "cr": 15.72}, {"name": "3235", "key": "3235", "cr": 21.91}, {"name": "3243", "key": "3243", "cr": 18.75}]}