{"name": "3361", "key": "3361", "state": "VIC", "pops": 698, "crime": {"total": 26, "Theft": 13, "Stalking, harassment and threatening behaviour": 1, "Justice procedures offences": 1, "Assault and related offences": 1, "Dangerous and negligent acts endangering people": 1, "Property damage": 3, "Burglary/Break and enter": 3, "Deception": 1, "Public nuisance offences": 1, "Breaches of orders": 1}, "crime_categories": {"property_crimes": {"number": 19, "rank": 69.4}, "violent_crimes": {"number": 1, "rank": 18.34}}, "bounds": [143.0721212960001, -37.84120529799998, 143.4647499130001, -37.611660729999976], "sqkm": 463.53240000000005, "cr": 27.52, "borders": [{"name": "3271", "key": "3271", "cr": 13.74}, {"name": "3324", "key": "3324", "cr": 31.32}, {"name": "3325", "key": "3325", "cr": 25.89}, {"name": "3351", "key": "3351", "cr": 56.91}, {"name": "3352", "key": "3352", "cr": 70.2}, {"name": "3360", "key": "3360", "cr": 28.13}, {"name": "3373", "key": "3373", "cr": 47.38}]}