{"name": "3501", "key": "3501", "state": "VIC", "pops": 2147, "crime": {"total": 62, "Burglary/Break and enter": 9, "Assault and related offences": 7, "Stalking, harassment and threatening behaviour": 2, "Other crimes against the person": 4, "Arson": 1, "Property damage": 6, "Theft": 14, "Breaches of orders": 10, "Miscellaneous offences": 2, "Dangerous and negligent acts endangering people": 1, "Deception": 2, "Cultivate or manufacture drugs": 1, "Drug use and possession": 1, "Disorderly and offensive conduct": 2}, "crime_categories": {"property_crimes": {"number": 30, "rank": 35.31}, "violent_crimes": {"number": 7, "rank": 29.42}}, "bounds": [141.99691755000003, -34.86447664599996, 142.51895623000004, -34.180737991999955], "sqkm": 1022.8817, "cr": 40.09, "borders": [{"name": "2648", "key": "2648", "cr": 57.21}, {"name": "2715", "key": "2715", "cr": 43.81}, {"name": "2737", "key": "2737", "cr": 26.39}, {"name": "2738", "key": "2738", "cr": 39.18}, {"name": "2739", "key": "2739", "cr": 47.91}, {"name": "3490", "key": "3490", "cr": 31.17}, {"name": "3494", "key": "3494", "cr": 30.52}, {"name": "3496", "key": "3496", "cr": 61.28}, {"name": "3498", "key": "3498", "cr": 55.35}, {"name": "3500", "key": "3500", "cr": 97.08}, {"name": "3505", "key": "3505", "cr": 60.78}, {"name": "3549", "key": "3549", "cr": 63.55}]}