{"name": "3562", "key": "3562", "state": "VIC", "pops": 257, "crime": {"total": 16, "Assault and related offences": 3, "Stalking, harassment and threatening behaviour": 1, "Other crimes against the person": 1, "Theft": 7, "Disorderly and offensive conduct": 2, "Breaches of orders": 1, "Miscellaneous offences": 1}, "crime_categories": {"property_crimes": {"number": 7, "rank": 68.83}, "violent_crimes": {"number": 3, "rank": 79.16}}, "bounds": [144.45716760800008, -36.11463457599996, 144.59999875800008, -35.944581851999956], "sqkm": 141.044, "cr": 23.8, "borders": [{"name": "2710", "key": "2710", "cr": 81.7}, {"name": "2731", "key": "2731", "cr": 63.48}, {"name": "3564", "key": "3564", "cr": 84.05}, {"name": "3573", "key": "3573", "cr": 27.94}]}