{"name": "3566", "key": "3566", "state": "VIC", "pops": 578, "crime": {"total": 13, "Stalking, harassment and threatening behaviour": 1, "Dangerous and negligent acts endangering people": 2, "Other crimes against the person": 1, "Property damage": 1, "Burglary/Break and enter": 3, "Theft": 3, "Deception": 1, "Justice procedures offences": 1}, "crime_categories": {"property_crimes": {"number": 7, "rank": 31.44}, "violent_crimes": {"number": 0, "rank": 0.0}}, "bounds": [144.25931746800006, -36.003284753999935, 144.44905906900007, -35.88412573599994], "sqkm": 131.534, "cr": 22.63, "borders": [{"name": "2710", "key": "2710", "cr": 82.65}, {"name": "2731", "key": "2731", "cr": 61.01}, {"name": "3564", "key": "3564", "cr": 87.78}, {"name": "3567", "key": "3567", "cr": 28.06}, {"name": "3568", "key": "3568", "cr": 46.28}, {"name": "3575", "key": "3575", "cr": 35.61}]}