{"name": "5010", "key": "5010", "state": "SA", "pops": 6110, "crime": {"total": 534, "Assault and related offences": 103, "Robbery": 3, "Stalking, harassment and threatening behaviour": 4, "Property damage": 109, "Burglary/Break and enter": 59, "Theft": 232, "Deception": 21, "Abduction and related offences": 3}, "crime_categories": {"property_crimes": {"number": 400, "rank": 92.44}, "violent_crimes": {"number": 109, "rank": 89.67}}, "bounds": [138.55567465500008, -34.87573409699996, 138.58162093000007, -34.849543326999964], "sqkm": 5.8507, "cr": 73.8, "borders": [{"name": "5008", "key": "5008", "cr": 86.26}, {"name": "5009", "key": "5009", "cr": 73.16}, {"name": "5012", "key": "5012", "cr": 80.52}, {"name": "5013", "key": "5013", "cr": 86.18}, {"name": "5082", "key": "5082", "cr": 82.99}, {"name": "5084", "key": "5084", "cr": 92.86}]}