{"name": "5040", "key": "5040", "state": "SA", "pops": 2508, "crime": {"total": 100, "Assault and related offences": 22, "Property damage": 27, "Burglary/Break and enter": 18, "Theft": 28, "Deception": 5}, "crime_categories": {"property_crimes": {"number": 73, "rank": 71.79}, "violent_crimes": {"number": 22, "rank": 68.87}}, "bounds": [138.52166768400002, -34.975601325999946, 138.53770888100001, -34.95800627599995], "sqkm": 1.7647, "cr": 50.27, "borders": [{"name": "5024", "key": "5024", "cr": 71.53}, {"name": "5037", "key": "5037", "cr": 72.4}, {"name": "5038", "key": "5038", "cr": 84.51}, {"name": "5045", "key": "5045", "cr": 86.79}, {"name": "5950", "key": "5950", "cr": 47.99}]}