{"name": "5120", "key": "5120", "state": "SA", "pops": 2858, "crime": {"total": 205, "Assault and related offences": 27, "Stalking, harassment and threatening behaviour": 1, "Property damage": 33, "Burglary/Break and enter": 23, "Theft": 109, "Abduction and related offences": 1, "Blackmail and extortion": 1, "Deception": 10}, "crime_categories": {"property_crimes": {"number": 165, "rank": 90.62}, "violent_crimes": {"number": 29, "rank": 74.83}}, "bounds": [138.43565228500006, -34.732276473999946, 138.60548814900005, -34.63445346699994], "sqkm": 86.1986, "cr": 56.8, "borders": [{"name": "5108", "key": "5108", "cr": 97.91}, {"name": "5110", "key": "5110", "cr": 78.93}, {"name": "5111", "key": "5111", "cr": 41.0}, {"name": "5121", "key": "5121", "cr": 39.64}, {"name": "5501", "key": "5501", "cr": 61.58}]}