{"name": "5134", "key": "5134", "state": "SA", "pops": 457, "crime": {"total": 3, "Assault and related offences": 1, "Burglary/Break and enter": 1, "Theft": 1}, "crime_categories": {"property_crimes": {"number": 2, "rank": 11.43}, "violent_crimes": {"number": 1, "rank": 23.65}}, "bounds": [138.7069753090001, -34.92030848699994, 138.8212677410001, -34.855886483999946], "sqkm": 36.5354, "cr": 13.9, "borders": [{"name": "5072", "key": "5072", "cr": 62.76}, {"name": "5073", "key": "5073", "cr": 68.03}, {"name": "5076", "key": "5076", "cr": 57.67}, {"name": "5089", "key": "5089", "cr": 52.2}, {"name": "5090", "key": "5090", "cr": 60.59}, {"name": "5132", "key": "5132", "cr": 35.35}, {"name": "5136", "key": "5136", "cr": 15.22}, {"name": "5137", "key": "5137", "cr": 23.39}, {"name": "5138", "key": "5138", "cr": 16.51}, {"name": "5139", "key": "5139", "cr": 19.74}, {"name": "5240", "key": "5240", "cr": 11.62}]}