{"name": "5253", "key": "5253", "state": "SA", "pops": 19267, "crime": {"total": 1417, "Assault and related offences": 356, "Theft": 505, "Deception": 54, "Property damage": 328, "Burglary/Break and enter": 136, "Abduction and related offences": 8, "Robbery": 3, "Blackmail and extortion": 2, "Stalking, harassment and threatening behaviour": 21, "Dangerous and negligent acts endangering people": 4}, "crime_categories": {"property_crimes": {"number": 969, "rank": 87.97}, "violent_crimes": {"number": 369, "rank": 91.42}}, "bounds": [139.1560460610001, -35.290445500999965, 139.6224315410001, -34.92684750299996], "sqkm": 874.8927000000001, "cr": 92.67, "borders": [{"name": "5237", "key": "5237", "cr": 18.34}, {"name": "5238", "key": "5238", "cr": 57.67}, {"name": "5254", "key": "5254", "cr": 48.52}, {"name": "5255", "key": "5255", "cr": 60.02}, {"name": "5259", "key": "5259", "cr": 35.19}, {"name": "5260", "key": "5260", "cr": 53.49}, {"name": "5301", "key": "5301", "cr": 20.05}, {"name": "5306", "key": "5306", "cr": 8.54}]}