{"name": "5485", "key": "5485", "state": "SA", "pops": 667, "crime": {"total": 8, "Assault and related offences": 1, "Abduction and related offences": 1, "Property damage": 2, "Burglary/Break and enter": 1, "Theft": 3}, "crime_categories": {"property_crimes": {"number": 6, "rank": 21.53}, "violent_crimes": {"number": 2, "rank": 29.92}}, "bounds": [138.00053046800008, -32.860930432999965, 138.28853542000007, -32.440842418999964], "sqkm": 601.736, "cr": 18.94, "borders": [{"name": "5431", "key": "5431", "cr": 18.6}, {"name": "5433", "key": "5433", "cr": 38.42}, {"name": "5482", "key": "5482", "cr": 15.72}, {"name": "5483", "key": "5483", "cr": 13.52}, {"name": "5495", "key": "5495", "cr": 26.77}, {"name": "5700", "key": "5700", "cr": 98.18}, {"name": "5701", "key": "5701", "cr": 0.0}]}