{"name": "6010", "key": "6010", "state": "WA", "pops": 18861, "crime": {"total": 1095, "Assault and related offences": 105, "Sexual offences": 20, "Abduction and related offences": 1, "Robbery": 5, "Stalking, harassment and threatening behaviour": 24, "Arson": 3, "Property damage": 83, "Burglary/Break and enter": 88, "Theft": 441, "Motor Vehicle Theft": 25, "Deception": 243, "Drug dealing and trafficking": 32, "Breaches of orders": 25}, "bounds": [115.75281683300011, -31.993526091999968, 115.8058907040001, -31.948232360999967], "cr": 82.8, "borders": [{"name": "6008", "key": "6008", "cr": 86.41}, {"name": "6009", "key": "6009", "cr": 81.06}, {"name": "6011", "key": "6011", "cr": 69.44}, {"name": "6014", "key": "6014", "cr": 79.46}, {"name": "6015", "key": "6015", "cr": 59.57}]}