{"name": "6025", "key": "6025", "state": "WA", "pops": 31587, "crime": {"total": 1505, "Homicide and related offences": 2, "Assault and related offences": 197, "Sexual offences": 52, "Abduction and related offences": 1, "Stalking, harassment and threatening behaviour": 23, "Arson": 3, "Property damage": 170, "Burglary/Break and enter": 92, "Theft": 436, "Motor Vehicle Theft": 23, "Deception": 156, "Drug dealing and trafficking": 186, "Breaches of orders": 151, "Robbery": 13}, "bounds": [115.72744296300004, -31.827248552999947, 115.78239414600004, -31.774955010999946], "cr": 89.1, "borders": [{"name": "6020", "key": "6020", "cr": 85.5}, {"name": "6024", "key": "6024", "cr": 84.93}, {"name": "6026", "key": "6026", "cr": 89.64}, {"name": "6027", "key": "6027", "cr": 96.96}, {"name": "6065", "key": "6065", "cr": 95.41}]}