{"name": "6060", "key": "6060", "state": "WA", "pops": 25530, "crime": {"total": 1853, "Assault and related offences": 239, "Sexual offences": 44, "Robbery": 9, "Stalking, harassment and threatening behaviour": 56, "Arson": 10, "Property damage": 176, "Burglary/Break and enter": 161, "Theft": 464, "Motor Vehicle Theft": 53, "Deception": 388, "Drug dealing and trafficking": 152, "Breaches of orders": 100, "Abduction and related offences": 1}, "bounds": [115.82828523600006, -31.914244637999957, 115.87258214000006, -31.88884655799996], "cr": 92.22, "borders": [{"name": "6006", "key": "6006", "cr": 77.52}, {"name": "6016", "key": "6016", "cr": 78.13}, {"name": "6017", "key": "6017", "cr": 75.21}, {"name": "6021", "key": "6021", "cr": 87.05}, {"name": "6050", "key": "6050", "cr": 79.99}, {"name": "6052", "key": "6052", "cr": 77.41}, {"name": "6059", "key": "6059", "cr": 84.32}, {"name": "6061", "key": "6061", "cr": 99.05}]}