{"name": "6108", "key": "6108", "state": "WA", "pops": 23665, "crime": {"total": 2327, "Assault and related offences": 267, "Sexual offences": 148, "Abduction and related offences": 1, "Robbery": 20, "Stalking, harassment and threatening behaviour": 62, "Arson": 3, "Property damage": 217, "Burglary/Break and enter": 239, "Theft": 623, "Motor Vehicle Theft": 38, "Deception": 319, "Drug dealing and trafficking": 303, "Breaches of orders": 87}, "bounds": [115.93029269300007, -32.082754041999976, 115.97821371700007, -32.03998659199998], "cr": 94.68, "borders": [{"name": "6107", "key": "6107", "cr": 99.16}, {"name": "6109", "key": "6109", "cr": 92.14}, {"name": "6110", "key": "6110", "cr": 98.03}, {"name": "6111", "key": "6111", "cr": 95.22}, {"name": "6147", "key": "6147", "cr": 86.48}, {"name": "6148", "key": "6148", "cr": 79.42}, {"name": "6155", "key": "6155", "cr": 94.53}]}