{"name": "6350", "key": "6350", "state": "WA", "pops": 334, "crime": {"total": 13, "Assault and related offences": 1, "Sexual offences": 1, "Stalking, harassment and threatening behaviour": 1, "Property damage": 2, "Burglary/Break and enter": 1, "Theft": 1, "Motor Vehicle Theft": 1, "Drug dealing and trafficking": 5}, "bounds": [117.62057264300006, -33.41392051599996, 118.04539947200006, -33.19563422099996], "cr": 21.94, "borders": [{"name": "6315", "key": "6315", "cr": 52.24}, {"name": "6316", "key": "6316", "cr": 20.05}, {"name": "6317", "key": "6317", "cr": 80.49}, {"name": "6341", "key": "6341", "cr": 19.25}, {"name": "6351", "key": "6351", "cr": 0.0}, {"name": "6352", "key": "6352", "cr": 17.54}]}