{"name": "6395", "key": "6395", "state": "WA", "pops": 1550, "crime": {"total": 179, "Sexual offences": 3, "Burglary/Break and enter": 24, "Motor Vehicle Theft": 1, "Assault and related offences": 20, "Abduction and related offences": 1, "Stalking, harassment and threatening behaviour": 4, "Arson": 1, "Property damage": 24, "Theft": 30, "Deception": 6, "Drug dealing and trafficking": 58, "Breaches of orders": 7}, "crime_categories": {"property_crimes": {"number": 80, "rank": 88.5}, "violent_crimes": {"number": 24, "rank": 86.52}}, "bounds": [116.79371474800007, -34.217949561999944, 117.35955250000006, -33.632977954999944], "sqkm": 1816.904, "cr": 53.99, "borders": [{"name": "6244", "key": "6244", "cr": 44.08}, {"name": "6258", "key": "6258", "cr": 69.7}, {"name": "6316", "key": "6316", "cr": 17.92}, {"name": "6317", "key": "6317", "cr": 80.56}, {"name": "6318", "key": "6318", "cr": 28.63}, {"name": "6320", "key": "6320", "cr": 39.26}, {"name": "6321", "key": "6321", "cr": 34.28}, {"name": "6393", "key": "6393", "cr": 15.22}, {"name": "6394", "key": "6394", "cr": 23.61}, {"name": "6396", "key": "6396", "cr": 17.2}]}