{"name": "6461", "key": "6461", "state": "WA", "pops": 490, "crime": {"total": 21, "Assault and related offences": 1, "Stalking, harassment and threatening behaviour": 3, "Property damage": 2, "Theft": 2, "Drug dealing and trafficking": 11, "Breaches of orders": 2}, "crime_categories": {"property_crimes": {"number": 4, "rank": 19.21}, "violent_crimes": {"number": 1, "rank": 22.85}}, "bounds": [116.93118628500008, -31.30814127499997, 117.19310259900008, -30.89940053899997], "sqkm": 648.859, "cr": 24.26, "borders": [{"name": "6460", "key": "6460", "cr": 48.22}, {"name": "6462", "key": "6462", "cr": 0.0}, {"name": "6465", "key": "6465", "cr": 0.0}, {"name": "6603", "key": "6603", "cr": 39.56}]}