{"name": "6608", "key": "6608", "state": "WA", "pops": 148, "crime": {"total": 3, "Stalking, harassment and threatening behaviour": 1, "Motor Vehicle Theft": 1, "Drug dealing and trafficking": 1}, "crime_categories": {"property_crimes": {"number": 1, "rank": 14.05}, "violent_crimes": {"number": 0, "rank": 0.0}}, "bounds": [116.49894246000008, -30.51695674499996, 116.91011044700008, -30.31069232399996], "sqkm": 749.9270999999999, "cr": 11.66, "borders": [{"name": "6468", "key": "6468", "cr": 16.78}, {"name": "6575", "key": "6575", "cr": 11.66}, {"name": "6606", "key": "6606", "cr": 25.32}, {"name": "6609", "key": "6609", "cr": 33.37}]}