{"name": "7179", "key": "7179", "state": "TAS", "pops": 422, "crime": {"total": 0}, "crime_categories": {"property_crimes": {"number": 0, "rank": 0.0}, "violent_crimes": {"number": 0, "rank": 0.0}}, "bounds": [147.8354280090001, -43.05834054999997, 147.98907889200012, -42.96274410199997], "sqkm": 51.4124, "cr": 0.0, "borders": [{"name": "7178", "key": "7178", "cr": 0.0}, {"name": "7180", "key": "7180", "cr": 0.0}, {"name": "7182", "key": "7182", "cr": 0.0}, {"name": "7187", "key": "7187", "cr": 0.0}]}