{"name": "7268", "key": "7268", "state": "TAS", "pops": 1132, "crime": {"total": 0}, "crime_categories": {"property_crimes": {"number": 0, "rank": 0.0}, "violent_crimes": {"number": 0, "rank": 0.0}}, "bounds": [147.12386110700004, -41.38061780999993, 147.30153910500005, -41.20187660099993], "sqkm": 162.4058, "cr": 0.0, "borders": [{"name": "7212", "key": "7212", "cr": 0.0}, {"name": "7248", "key": "7248", "cr": 0.0}, {"name": "7252", "key": "7252", "cr": 0.0}, {"name": "7254", "key": "7254", "cr": 0.0}, {"name": "7259", "key": "7259", "cr": 0.0}, {"name": "7260", "key": "7260", "cr": 0.0}, {"name": "7267", "key": "7267", "cr": 0.0}]}