{"name": "Central Coast (Tas.)", "key": "central-coast-tas", "state": "TAS", "pops": 22885, "crime": {"total": 0}, "crime_categories": {"property_crimes": {"number": 0, "rank": 0.0}, "violent_crimes": {"number": 0, "rank": 0.0}}, "bounds": [145.845239751, -41.465850021999984, 146.27309644500008, -41.07409493899996], "sqkm": 900.0555999999997, "mcr": 0.0, "cr": 0, "borders": [{"name": "Burnie", "key": "burnie", "cr": 0}, {"name": "Devonport", "key": "devonport", "cr": 0}, {"name": "Kentish", "key": "kentish", "cr": 0}, {"name": "Meander Valley", "key": "meander-valley", "cr": 0}, {"name": "Waratah-Wynyard", "key": "waratahwynyard", "cr": 0}]}