{"name": "Exmouth", "key": "exmouth", "state": "WA", "pops": 3082, "crime": {"total": 176, "Assault and related offences": 36, "Sexual offences": 3, "Stalking, harassment and threatening behaviour": 2, "Property damage": 29, "Burglary/Break and enter": 1, "Theft": 60, "Motor Vehicle Theft": 7, "Deception": 2, "Drug dealing and trafficking": 31, "Breaches of orders": 5}, "bounds": [113.65402230400002, -23.01125271799998, 114.75400552000008, -21.624413223999966], "cr": 29.83, "borders": [{"name": "Ashburton", "key": "ashburton", "cr": 51.2}, {"name": "Carnarvon", "key": "carnarvon", "cr": 72.38}]}