{"name": "Lake Grace", "key": "lake-grace", "state": "WA", "pops": 1261, "crime": {"total": 24, "Assault and related offences": 7, "Sexual offences": 2, "Property damage": 1, "Burglary/Break and enter": 2, "Theft": 5, "Deception": 1, "Drug dealing and trafficking": 6}, "crime_categories": {"property_crimes": {"number": 8, "rank": 10.68}, "violent_crimes": {"number": 9, "rank": 43.28}}, "bounds": [118.25969242300005, -33.540172465999945, 120.58148782600006, -32.71788443999998], "sqkm": 10291.594799999997, "mcr": 0.0, "cr": 18, "borders": [{"name": "Dumbleyung", "key": "dumbleyung", "cr": 15}, {"name": "Dundas", "key": "dundas", "cr": 100}, {"name": "Esperance", "key": "esperance", "cr": 64}, {"name": "Jerramungup", "key": "jerramungup", "cr": 51}, {"name": "Kent", "key": "kent", "cr": 16}, {"name": "Kondinin", "key": "kondinin", "cr": 59}, {"name": "Kulin", "key": "kulin", "cr": 27}, {"name": "Ravensthorpe", "key": "ravensthorpe", "cr": 22}]}