{"name": "Melville", "key": "melville", "state": "WA", "pops": 106123, "crime": {"total": 6520, "Assault and related offences": 632, "Stalking, harassment and threatening behaviour": 146, "Property damage": 516, "Burglary/Break and enter": 710, "Theft": 2290, "Motor Vehicle Theft": 157, "Deception": 1339, "Drug dealing and trafficking": 281, "Breaches of orders": 175, "Sexual offences": 205, "Robbery": 50, "Arson": 15, "Abduction and related offences": 3, "Homicide and related offences": 1}, "crime_categories": {"property_crimes": {"number": 3688, "rank": 70.17}, "violent_crimes": {"number": 891, "rank": 49.17}}, "bounds": [115.7761727730001, -32.08546461699996, 115.89211896100005, -32.001648047999936], "sqkm": 54.2092, "mcr": 0.14, "cr": 54.33, "borders": [{"name": "Canning", "key": "canning", "cr": 78.64}, {"name": "Cockburn", "key": "cockburn", "cr": 72.56}, {"name": "East Fremantle", "key": "east-fremantle", "cr": 62.06}, {"name": "Fremantle", "key": "fremantle", "cr": 91.53}, {"name": "Mosman Park", "key": "mosman-park", "cr": 52.85}, {"name": "Nedlands", "key": "nedlands", "cr": 34.99}, {"name": "South Perth", "key": "south-perth", "cr": 77.53}, {"name": "Victoria Park", "key": "victoria-park", "cr": 90.42}]}