{"name": "Mundaring", "key": "mundaring", "state": "WA", "pops": 44328, "crime": {"total": 2470, "Assault and related offences": 450, "Stalking, harassment and threatening behaviour": 105, "Arson": 20, "Property damage": 334, "Theft": 481, "Drug dealing and trafficking": 247, "Sexual offences": 116, "Abduction and related offences": 6, "Burglary/Break and enter": 251, "Motor Vehicle Theft": 67, "Deception": 174, "Breaches of orders": 205, "Robbery": 13, "Homicide and related offences": 1}, "bounds": [116.0148036700001, -32.062547621999954, 116.41513569300002, -31.706537671999968], "cr": 74.4, "borders": [{"name": "Beverley", "key": "beverley", "cr": 25.05}, {"name": "Gosnells", "key": "gosnells", "cr": 95.03}, {"name": "Kalamunda", "key": "kalamunda", "cr": 73.48}, {"name": "Northam", "key": "northam", "cr": 65.01}, {"name": "Swan", "key": "swan", "cr": 96.87}, {"name": "Toodyay", "key": "toodyay", "cr": 30.57}, {"name": "York", "key": "york", "cr": 29.65}]}