{"name": "Queenscliffe", "key": "queenscliffe", "state": "VIC", "pops": 1516, "crime": {"total": 39, "Assault and related offences": 2, "Dangerous and negligent acts endangering people": 1, "Other crimes against the person": 2, "Property damage": 6, "Theft": 17, "Deception": 2, "Transport regulation offences": 7, "Miscellaneous offences": 2}, "bounds": [144.60075082900005, -38.29212968699994, 144.7020153960001, -38.23782656099996], "cr": 14.73, "borders": [{"name": "Greater Geelong", "key": "greater-geelong", "cr": 96.5}, {"name": "Mornington Peninsula", "key": "mornington-peninsula", "cr": 84.35}, {"name": "Unincorporated Vic", "key": "unincorporated-vic", "cr": 9.58}]}