{"name": "Yalgoo", "key": "yalgoo", "state": "WA", "pops": 339, "crime": {"total": 23, "Assault and related offences": 6, "Sexual offences": 1, "Stalking, harassment and threatening behaviour": 3, "Property damage": 6, "Burglary/Break and enter": 3, "Theft": 1, "Breaches of orders": 3}, "crime_categories": {"property_crimes": {"number": 10, "rank": 64.46}, "violent_crimes": {"number": 7, "rank": 85.08}}, "bounds": [116.0326024090001, -29.801310530999956, 118.2838709350001, -27.17440051099993], "sqkm": 27949.399999999998, "mcr": 0.26, "cr": 82.14, "borders": [{"name": "Carnamah", "key": "carnamah", "cr": 52.12}, {"name": "Coorow", "key": "coorow", "cr": 27.26}, {"name": "Cue", "key": "cue", "cr": 95.21}, {"name": "Dalwallinu", "key": "dalwallinu", "cr": 26.52}, {"name": "Greater Geraldton", "key": "greater-geraldton", "cr": 92.45}, {"name": "Meekatharra", "key": "meekatharra", "cr": 98.9}, {"name": "Morawa", "key": "morawa", "cr": 85.08}, {"name": "Mount Magnet", "key": "mount-magnet", "cr": 97.61}, {"name": "Mount Marshall", "key": "mount-marshall", "cr": 13.81}, {"name": "Murchison", "key": "murchison", "cr": 94.29}, {"name": "Perenjori", "key": "perenjori", "cr": 10.31}, {"name": "Sandstone", "key": "sandstone", "cr": 92.08}]}