{"name": "Yorke Peninsula", "key": "yorke-peninsula", "state": "SA", "pops": 11471, "crime": {"total": 201, "Property damage": 45, "Assault and related offences": 53, "Stalking, harassment and threatening behaviour": 5, "Burglary/Break and enter": 33, "Theft": 45, "Deception": 16, "Abduction and related offences": 2, "Dangerous and negligent acts endangering people": 2}, "bounds": [136.82218352300004, -35.377975624999976, 138.1278465160001, -34.084943521999946], "cr": 34.25, "borders": [{"name": "Barunga West", "key": "barunga-west", "cr": 24.31}, {"name": "Copper Coast", "key": "copper-coast", "cr": 51.75}, {"name": "Wakefield", "key": "wakefield", "cr": 32.04}, {"name": "Yankalilla", "key": "yankalilla", "cr": 31.12}, {"name": "Unincorporated SA", "key": "unincorporated-sa", "cr": 38.49}]}