{"name": "Cullinane", "key": "cullinane", "pops": 524, "cr": 11, "bounds": [146.0105580613, -17.5158298761, 146.0348118097, -17.5071365461], "crime": {"total": 21, "Traffic and Related Offences": 1, "Unlawful Entry": 4, "Good Order Offences": 2, "Drug Offences": 3, "Liquor (excl. Drunkenness)": 1, "Other Theft (excl. Unlawful Entry)": 1, "Assault": 4, "Other Offences Against the Person": 1, "Other Property Damage": 1, "Handling Stolen Goods": 1, "Fraud": 1, "Trespassing and Vagrancy": 1}, "borders": [{"name": "Goondi Hill", "key": "goondi-hill", "cr": 38}, {"name": "Goondi Bend", "key": "goondi-bend", "cr": 20}, {"name": "Goondi", "key": "goondi", "cr": 21}, {"name": "Innisfail Estate", "key": "innisfail-estate", "cr": 20}, {"name": "Innisfail", "key": "innisfail", "cr": 100}, {"name": "Sundown - Cassowary Coast", "key": "sundown-cassowary-coast", "cr": 0}], "polygon": [[146.0110000446, -17.507177785], [146.0108074844, -17.5084149539], [146.0137578696, -17.5144752115], [146.0313956514, -17.5158298761], [146.0348118097, -17.5105288252], [146.0300763026, -17.5087261945], [146.0110000446, -17.507177785]]}