{"name": "Sandstone Point", "key": "sandstone-point", "pops": 3959, "cr": 8, "bounds": [153.1144146174, -27.0968792513, 153.1595154852, -27.0579617769], "crime": {"total": 198, "Good Order Offences": 26, "Assault": 17, "Other Theft (excl. Unlawful Entry)": 41, "Unlawful Entry": 9, "Other Property Damage": 21, "Drug Offences": 40, "Liquor (excl. Drunkenness)": 7, "Weapons Act Offences": 5, "Traffic and Related Offences": 21, "Fraud": 4, "Unlawful Use of Motor Vehicle": 4, "Other Offences Against the Person": 2, "Trespassing and Vagrancy": 1}, "borders": [{"name": "Banksia Beach", "key": "banksia-beach", "cr": 5}, {"name": "Bellara", "key": "bellara", "cr": 14}, {"name": "Bongaree", "key": "bongaree", "cr": 12}, {"name": "Godwin Beach", "key": "godwin-beach", "cr": 8}, {"name": "Ningi", "key": "ningi", "cr": 8}, {"name": "Toorbul", "key": "toorbul", "cr": 8}], "polygon": [[153.1306524947, -27.0579617769], [153.1265475079, -27.060046792], [153.1194525287, -27.0587827712], [153.1144146174, -27.0857342035], [153.1202775165, -27.0849999338], [153.1225352958, -27.0865900218], [153.1300310642, -27.0869239345], [153.1330212057, -27.0859389976], [153.1595154852, -27.0968792513], [153.1533002928, -27.0775236487], [153.1506363899, -27.0741177276], [153.1415044293, -27.0695597604], [153.1376913935, -27.0662817433], [153.1315044761, -27.0602407455], [153.1306524947, -27.0579617769]]}